<?xml version="1.0" encoding="UTF-8" standalone="yes"?>
<features name="org.opennms.features.bsm.shell-commands" xmlns="http://karaf.apache.org/xmlns/features/v1.2.0">
    <feature name="org.opennms.features.bsm.shell-commands" version="${project.version}" description="OpenNMS :: Features :: BSM :: Shell Commands">
        <bundle>mvn:org.opennms.features.bsm/org.opennms.features.bsm.shell-commands/${project.version}</bundle>
        <bundle>mvn:org.opennms.features.bsm/org.opennms.features.bsm.service.api/${project.version}</bundle>
        <bundle>mvn:org.apache.karaf.shell/org.apache.karaf.shell.core/${karafVersion}</bundle>
    </feature>
</features>
